kanban/__init__.py
kanban/cli.py
kanban/models/__init__.py
kanban/models/board.py
kanban/models/gitlab.py
kanban/models/issue.py
kanban/models/label.py
gitlab_kanban-0.0.1.dist-info/LICENSE
gitlab_kanban-0.0.1.dist-info/METADATA
gitlab_kanban-0.0.1.dist-info/WHEEL
gitlab_kanban-0.0.1.dist-info/entry_points.txt
gitlab_kanban-0.0.1.dist-info/top_level.txt
gitlab_kanban-0.0.1.dist-info/RECORD
