Metadata-Version: 2.1
Name: gitlab-kanban
Version: 0.0.1
Summary: GitLab Kanban Board Command Line Interface
Home-page: https://github.com/rofrano/gitlab-kanban
Author: John Rofrano
Author-email: rofrano@gmail.com
License: Apache
Keywords: gitlab kanban
Classifier: Development Status :: 2 - Pre-Alpha
Classifier: Environment :: Console
Classifier: Intended Audience :: Developers
Classifier: License :: OSI Approved :: Apache Software License
Classifier: Operating System :: OS Independent
Classifier: Programming Language :: Python
Classifier: Programming Language :: Python :: 3
Classifier: Programming Language :: Python :: 3.9
Requires-Python: >=3.9.0
License-File: LICENSE
Requires-Dist: click (==8.1.3)
Requires-Dist: requests (==2.27.1)
Requires-Dist: tqdm (==4.64.0)
Provides-Extra: dev
Requires-Dist: nose (==1.3.7) ; extra == 'dev'
Requires-Dist: pinocchio (==0.4.3) ; extra == 'dev'
Requires-Dist: coverage (==6.3.2) ; extra == 'dev'
Requires-Dist: pylint (==2.13) ; extra == 'dev'
Requires-Dist: flake8 (==4.0.1) ; extra == 'dev'
Requires-Dist: black (==22.3.0) ; extra == 'dev'
